MANIFEST.in
README.md
setup.py
flask_easymode/__init__.py
flask_easymode/decorators.py
flask_easymode/exceptions.py
flask_easymode/helpers.py
flask_easymode.egg-info/PKG-INFO
flask_easymode.egg-info/SOURCES.txt
flask_easymode.egg-info/dependency_links.txt
flask_easymode.egg-info/requires.txt
flask_easymode.egg-info/top_level.txt
flask_easymode/mixins/__init__.py
flask_easymode/mixins/model.py
flask_easymode/tests/__init__.py
flask_easymode/tests/test_decorators.py
flask_easymode/tests/test_mixins/__init__.py
flask_easymode/tests/test_mixins/test_model.py