Metadata-Version: 1.1
Name: flask-easymode
Version: 0.0.13
Summary: Make Flask development even easier
Home-page: http://github.com/petermelias/flask-easymode
Author: Peter M. Elias
Author-email: petermelias@gmail.com
License: MIT
Platform: any
Classifier: Environment :: Web Environment
Classifier: Intended Audience :: Developers
Classifier: License :: OSI Approved :: MIT License
Classifier: Operating System :: OS Independent
Classifier: Programming Language :: Python
Classifier: Topic :: Internet :: WWW/HTTP :: Dynamic Content
Classifier: Topic :: Software Development :: Libraries :: Python Modules
